qthreading/__init__.py
qthreading/qthreading.cp37-win_amd64.pyd
qthreading-0.0.1.1.dist-info/LICENSE.txt
qthreading-0.0.1.1.dist-info/METADATA
qthreading-0.0.1.1.dist-info/WHEEL
qthreading-0.0.1.1.dist-info/top_level.txt
qthreading-0.0.1.1.dist-info/RECORD
