Metadata-Version: 2.1
Name: qthreading
Version: 0.0.1.1
Summary: balanced threadpool
Home-page: UNKNOWN
Author: laghmari khalil
Author-email: laghmari.khalil@gmail.com
License: MIT
Keywords: thread,pool,balance
Platform: UNKNOWN
